setup.cfg
setup.py
src/vmw/__init__.py
src/vmw.vco.egg-info/PKG-INFO
src/vmw.vco.egg-info/SOURCES.txt
src/vmw.vco.egg-info/dependency_links.txt
src/vmw.vco.egg-info/namespace_packages.txt
src/vmw.vco.egg-info/requires.txt
src/vmw.vco.egg-info/top_level.txt
src/vmw/vco/__init__.py
src/vmw/vco/adapters.py
src/vmw/vco/client.py
src/vmw/vco/components.py
src/vmw/vco/interfaces.py
src/vmw/vco/types.py
src/vmw/vco/generated/VSOWebControlService_client_async.py
src/vmw/vco/generated/VSOWebControlService_client_sync.py
src/vmw/vco/generated/VSOWebControlService_server.py
src/vmw/vco/generated/VSOWebControlService_types.py
src/vmw/vco/generated/__init__.py