Metadata-Version: 1.0
Name: vmw.vco
Version: 0.3.1
Summary: Python bindings for the VMware Orchestrator
Home-page: http://sigma.github.com/vmw.vco
Author: Yann Hodique
Author-email: yhodique@vmware.com
License: MIT
Platform: UNKNOWN
